jdtaxcalculator/__init__.py
jdtaxcalculator/uk_tax_calculator.py
jdtaxcalculator-0.0.6.dist-info/LICENSE
jdtaxcalculator-0.0.6.dist-info/METADATA
jdtaxcalculator-0.0.6.dist-info/WHEEL
jdtaxcalculator-0.0.6.dist-info/top_level.txt
jdtaxcalculator-0.0.6.dist-info/RECORD
