Metadata-Version: 2.1
Name: jdtaxcalculator
Version: 0.0.6
Summary: UK Tax Calculator
Author-email: Jack Dyer <jack.dyer387@gmail.com>
Project-URL: Homepage, https://github.com/jackLDyer/uk-tax-calculator
Project-URL: Issues, https://github.com/jackLDyer/uk-tax-calculator/issues
Classifier: Programming Language :: Python :: 3
Classifier: License :: OSI Approved :: MIT License
Classifier: Operating System :: OS Independent
Requires-Python: >=3.11
License-File: LICENSE
